zeph1rr_fastapi/__init__.py
zeph1rr_fastapi/__main__.py
zeph1rr_fastapi/logging.py
zeph1rr_fastapi/models.py
zeph1rr_fastapi/utils.py
zeph1rr_fastapi-1.1.0.dist-info/LICENSE.md
zeph1rr_fastapi-1.1.0.dist-info/METADATA
zeph1rr_fastapi-1.1.0.dist-info/WHEEL
zeph1rr_fastapi-1.1.0.dist-info/RECORD
