Metadata-Version: 2.1
Name: zeph1rr-fastapi
Version: 1.1.0
Summary: 
Author: Zeph1rr
Author-email: grianton535@gmail.com
Requires-Python: >=3.12,<4.0
Classifier: Programming Language :: Python :: 3
Classifier: Programming Language :: Python :: 3.12
Requires-Dist: fastapi (>=0.110.0,<0.111.0)
Requires-Dist: loguru (>=0.7.2,<0.8.0)
Requires-Dist: pydantic (>=2.6.4,<3.0.0)
Requires-Dist: python-jose (>=3.3.0,<4.0.0)
Requires-Dist: tomli (>=2.0.1,<3.0.0)
Requires-Dist: uvicorn (>=0.28.0,<0.29.0)
